chekversi/__init__.py
chekversi/main.py
chekversi-0.1.0.dist-info/LICENCE.txt
chekversi-0.1.0.dist-info/METADATA
chekversi-0.1.0.dist-info/WHEEL
chekversi-0.1.0.dist-info/entry_points.txt
chekversi-0.1.0.dist-info/top_level.txt
chekversi-0.1.0.dist-info/RECORD
